{
  "date": "2022-07-27 18:00:00",
  "map_stats": [
    {
      "flat_players": [
        {
          "kills": "280",
          "name": "Tooug",
          "team": "puGG"
        },
        {
          "kills": "292",
          "name": "Celin",
          "team": "puGG"
        },
        {
          "kills": "187",
          "name": "Igaum",
          "team": "puGG"
        },
        {
          "kills": "223",
          "name": "Siduzord",
          "team": "puGG"
        },
        {
          "kills": "232",
          "name": "ind1n",
          "team": "puGG"
        },
        {
          "kills": "257",
          "name": "m4ndzin",
          "team": "ODDIK Bright"
        },
        {
          "kills": "224",
          "name": "isla",
          "team": "ODDIK Bright"
        },
        {
          "kills": "149",
          "name": "nAny",
          "team": "ODDIK Bright"
        },
        {
          "kills": "121",
          "name": "Aninha",
          "team": "ODDIK Bright"
        },
        {
          "kills": "81",
          "name": "mindle",
          "team": "ODDIK Bright"
        }
      ],
      "halftime_score": null,
      "map": "Haven",
      "players": [
        [
          {
            "acs": "1.70\n0.62\n1.97",
            "adr": "+13\n0\n+13",
            "agent": "",
            "assists": "/\n\n6\n2\n4\n\n/",
            "deaths": "19\n2\n17",
            "fk": "161\n77\n183",
            "hs%": "80%\n67%\n83%",
            "kdr": "4\n0\n4",
            "kills": "280",
            "name": "Tooug",
            "team": "puGG"
          },
          {
            "acs": "1.67\n4.04\n1.08",
            "adr": "+7\n+7\n0",
            "agent": "",
            "assists": "/\n\n8\n0\n8\n\n/",
            "deaths": "15\n7\n8",
            "fk": "175\n242\n159",
            "hs%": "87%\n100%\n83%",
            "kdr": "11\n2\n9",
            "kills": "292",
            "name": "Celin",
            "team": "puGG"
          },
          {
            "acs": "1.34\n0.95\n1.44",
            "adr": "+6\n0\n+6",
            "agent": "",
            "assists": "/\n\n5\n1\n4\n\n/",
            "deaths": "11\n1\n10",
            "fk": "119\n73\n131",
            "hs%": "80%\n67%\n83%",
            "kdr": "2\n2\n0",
            "kills": "187",
            "name": "Igaum",
            "team": "puGG"
          },
          {
            "acs": "1.08\n2.13\n0.82",
            "adr": "+4\n+3\n+1",
            "agent": "",
            "assists": "/\n\n9\n1\n8\n\n/",
            "deaths": "13\n4\n9",
            "fk": "146\n211\n130",
            "hs%": "80%\n100%\n75%",
            "kdr": "7\n3\n4",
            "kills": "223",
            "name": "Siduzord",
            "team": "puGG"
          },
          {
            "acs": "1.06\n0.53\n1.19",
            "adr": "0\n-2\n+2",
            "agent": "",
            "assists": "/\n\n11\n3\n8\n\n/",
            "deaths": "11\n1\n10",
            "fk": "159\n94\n175",
            "hs%": "80%\n100%\n75%",
            "kdr": "7\n2\n5",
            "kills": "232",
            "name": "ind1n",
            "team": "puGG"
          }
        ],
        [
          {
            "acs": "1.15\n1.30\n0.54",
            "adr": "-2\n-1\n-1",
            "agent": "",
            "assists": "/\n\n13\n10\n3\n\n/",
            "deaths": "11\n9\n2",
            "fk": "169\n187\n99",
            "hs%": "67%\n75%\n33%",
            "kdr": "5\n5\n0",
            "kills": "257",
            "name": "m4ndzin",
            "team": "ODDIK Bright"
          },
          {
            "acs": "0.91\n0.94\n0.82",
            "adr": "-2\n-2\n0",
            "agent": "",
            "assists": "/\n\n14\n11\n3\n\n/",
            "deaths": "12\n9\n3",
            "fk": "138\n133\n157",
            "hs%": "60%\n50%\n100%",
            "kdr": "0\n0\n0",
            "kills": "224",
            "name": "isla",
            "team": "ODDIK Bright"
          },
          {
            "acs": "0.57\n0.63\n0.36",
            "adr": "-6\n-5\n-1",
            "agent": "",
            "assists": "/\n\n14\n11\n3\n\n/",
            "deaths": "8\n6\n2",
            "fk": "96\n106\n57",
            "hs%": "73%\n75%\n67%",
            "kdr": "4\n4\n0",
            "kills": "149",
            "name": "nAny",
            "team": "ODDIK Bright"
          },
          {
            "acs": "0.43\n0.59\n0.01",
            "adr": "-8\n-5\n-3",
            "agent": "",
            "assists": "/\n\n14\n11\n3\n\n/",
            "deaths": "6\n6\n0",
            "fk": "76\n84\n45",
            "hs%": "53%\n58%\n33%",
            "kdr": "4\n3\n1",
            "kills": "121",
            "name": "Aninha",
            "team": "ODDIK Bright"
          },
          {
            "acs": "0.18\n0.23\n0.03",
            "adr": "-12\n-9\n-3",
            "agent": "",
            "assists": "/\n\n14\n11\n3\n\n/",
            "deaths": "2\n2\n0",
            "fk": "70\n78\n38",
            "hs%": "40%\n42%\n33%",
            "kdr": "4\n3\n1",
            "kills": "81",
            "name": "mindle",
            "team": "ODDIK Bright"
          }
        ]
      ],
      "round_results": [],
      "total_score": null
    },
    {
      "flat_players": [
        {
          "kills": "100",
          "name": "Tooug",
          "team": null
        },
        {
          "kills": "552",
          "name": "Celin",
          "team": null
        },
        {
          "kills": "113",
          "name": "Igaum",
          "team": null
        },
        {
          "kills": "366",
          "name": "Siduzord",
          "team": null
        },
        {
          "kills": "126",
          "name": "ind1n",
          "team": null
        },
        {
          "kills": "274",
          "name": "m4ndzin",
          "team": null
        },
        {
          "kills": "214",
          "name": "isla",
          "team": null
        },
        {
          "kills": "152",
          "name": "nAny",
          "team": null
        },
        {
          "kills": "140",
          "name": "Aninha",
          "team": null
        },
        {
          "kills": "93",
          "name": "mindle",
          "team": null
        }
      ],
      "halftime_score": null,
      "map": "",
      "players": [
        [
          {
            "acs": "0.62\n1.97\n1.70",
            "adr": "+13\n0\n+13",
            "agent": "",
            "assists": "/\n\n6\n2\n4\n\n/",
            "deaths": "19\n2\n17",
            "fk": "161\n77\n183",
            "hs%": "80%\n67%\n83%",
            "kdr": "4\n0\n4",
            "kills": "100",
            "name": "Tooug",
            "team": null
          },
          {
            "acs": "4.04\n1.08\n1.67",
            "adr": "+7\n+7\n0",
            "agent": "",
            "assists": "/\n\n8\n0\n8\n\n/",
            "deaths": "15\n7\n8",
            "fk": "175\n242\n159",
            "hs%": "87%\n100%\n83%",
            "kdr": "11\n2\n9",
            "kills": "552",
            "name": "Celin",
            "team": null
          },
          {
            "acs": "0.95\n1.44\n1.34",
            "adr": "+6\n0\n+6",
            "agent": "",
            "assists": "/\n\n5\n1\n4\n\n/",
            "deaths": "11\n1\n10",
            "fk": "119\n73\n131",
            "hs%": "80%\n67%\n83%",
            "kdr": "2\n2\n0",
            "kills": "113",
            "name": "Igaum",
            "team": null
          },
          {
            "acs": "2.13\n0.82\n1.08",
            "adr": "+4\n+3\n+1",
            "agent": "",
            "assists": "/\n\n9\n1\n8\n\n/",
            "deaths": "13\n4\n9",
            "fk": "146\n211\n130",
            "hs%": "80%\n100%\n75%",
            "kdr": "7\n3\n4",
            "kills": "366",
            "name": "Siduzord",
            "team": null
          },
          {
            "acs": "0.53\n1.19\n1.06",
            "adr": "0\n-2\n+2",
            "agent": "",
            "assists": "/\n\n11\n3\n8\n\n/",
            "deaths": "11\n1\n10",
            "fk": "159\n94\n175",
            "hs%": "80%\n100%\n75%",
            "kdr": "7\n2\n5",
            "kills": "126",
            "name": "ind1n",
            "team": null
          }
        ],
        [
          {
            "acs": "1.30\n0.54\n1.15",
            "adr": "-2\n-1\n-1",
            "agent": "",
            "assists": "/\n\n13\n10\n3\n\n/",
            "deaths": "11\n9\n2",
            "fk": "169\n187\n99",
            "hs%": "67%\n75%\n33%",
            "kdr": "5\n5\n0",
            "kills": "274",
            "name": "m4ndzin",
            "team": null
          },
          {
            "acs": "0.94\n0.82\n0.91",
            "adr": "-2\n-2\n0",
            "agent": "",
            "assists": "/\n\n14\n11\n3\n\n/",
            "deaths": "12\n9\n3",
            "fk": "138\n133\n157",
            "hs%": "60%\n50%\n100%",
            "kdr": "0\n0\n0",
            "kills": "214",
            "name": "isla",
            "team": null
          },
          {
            "acs": "0.63\n0.36\n0.57",
            "adr": "-6\n-5\n-1",
            "agent": "",
            "assists": "/\n\n14\n11\n3\n\n/",
            "deaths": "8\n6\n2",
            "fk": "96\n106\n57",
            "hs%": "73%\n75%\n67%",
            "kdr": "4\n4\n0",
            "kills": "152",
            "name": "nAny",
            "team": null
          },
          {
            "acs": "0.59\n0.01\n0.43",
            "adr": "-8\n-5\n-3",
            "agent": "",
            "assists": "/\n\n14\n11\n3\n\n/",
            "deaths": "6\n6\n0",
            "fk": "76\n84\n45",
            "hs%": "53%\n58%\n33%",
            "kdr": "4\n3\n1",
            "kills": "140",
            "name": "Aninha",
            "team": null
          },
          {
            "acs": "0.23\n0.03\n0.18",
            "adr": "-12\n-9\n-3",
            "agent": "",
            "assists": "/\n\n14\n11\n3\n\n/",
            "deaths": "2\n2\n0",
            "fk": "70\n78\n38",
            "hs%": "40%\n42%\n33%",
            "kdr": "4\n3\n1",
            "kills": "93",
            "name": "mindle",
            "team": null
          }
        ]
      ],
      "round_results": [],
      "total_score": null
    }
  ],
  "maps": [],
  "match_id": 123190,
  "teams": [
    "puGG",
    "ODDIK Bright"
  ],
  "tournament": "Diamond Stage: \n\t\t\t\t\t\tRound 3"
}