{
  "date": "2021-07-31 08:30:00",
  "map_stats": [
    {
      "flat_players": [
        {
          "kills": "332",
          "name": "Aanszo",
          "team": "uhrbtgjmny8"
        },
        {
          "kills": "233",
          "name": "bryce",
          "team": "uhrbtgjmny8"
        },
        {
          "kills": "130",
          "name": "JayH",
          "team": "uhrbtgjmny8"
        },
        {
          "kills": "173",
          "name": "Flaring",
          "team": "uhrbtgjmny8"
        },
        {
          "kills": "59",
          "name": "alfin",
          "team": "uhrbtgjmny8"
        },
        {
          "kills": "345",
          "name": "Xenoo",
          "team": "Origin Sky"
        },
        {
          "kills": "316",
          "name": "IcaaaPftw",
          "team": "Origin Sky"
        },
        {
          "kills": "213",
          "name": "kayle",
          "team": "Origin Sky"
        },
        {
          "kills": "145",
          "name": "haze",
          "team": "Origin Sky"
        },
        {
          "kills": "153",
          "name": "markL",
          "team": "Origin Sky"
        }
      ],
      "halftime_score": null,
      "map": "Bind",
      "players": [
        [
          {
            "acs": "1.30\n1.84\n0.36",
            "adr": "+4\n+8\n-4",
            "agent": "",
            "assists": "/\n\n17\n12\n5\n\n/",
            "deaths": "21\n20\n1",
            "fk": "205\n263\n107",
            "hs%": "68%\n75%\n57%",
            "kdr": "5\n1\n4",
            "kills": "332",
            "name": "Aanszo",
            "team": "uhrbtgjmny8"
          },
          {
            "acs": "1.18\n1.06\n1.40",
            "adr": "+2\n-1\n+3",
            "agent": "",
            "assists": "/\n\n15\n9\n6\n\n/",
            "deaths": "17\n8\n9",
            "fk": "159\n138\n194",
            "hs%": "84%\n92%\n71%",
            "kdr": "9\n8\n1",
            "kills": "233",
            "name": "bryce",
            "team": "uhrbtgjmny8"
          },
          {
            "acs": "0.56\n0.76\n0.21",
            "adr": "-9\n-4\n-5",
            "agent": "",
            "assists": "/\n\n15\n9\n6\n\n/",
            "deaths": "6\n5\n1",
            "fk": "89\n119\n37",
            "hs%": "53%\n58%\n43%",
            "kdr": "6\n3\n3",
            "kills": "130",
            "name": "JayH",
            "team": "uhrbtgjmny8"
          },
          {
            "acs": "0.54\n0.35\n0.88",
            "adr": "-7\n-8\n+1",
            "agent": "",
            "assists": "/\n\n17\n13\n4\n\n/",
            "deaths": "10\n5\n5",
            "fk": "112\n102\n128",
            "hs%": "63%\n58%\n71%",
            "kdr": "6\n3\n3",
            "kills": "173",
            "name": "Flaring",
            "team": "uhrbtgjmny8"
          },
          {
            "acs": "0.16\n0.26\n0.03",
            "adr": "-13\n-7\n-6",
            "agent": "",
            "assists": "/\n\n17\n10\n7\n\n/",
            "deaths": "4\n3\n1",
            "fk": "44\n54\n27",
            "hs%": "37%\n50%\n14%",
            "kdr": "3\n3\n0",
            "kills": "59",
            "name": "alfin",
            "team": "uhrbtgjmny8"
          }
        ],
        [
          {
            "acs": "1.88\n1.89\n1.88",
            "adr": "+13\n+5\n+8",
            "agent": "",
            "assists": "/\n\n10\n3\n7\n\n/",
            "deaths": "23\n8\n15",
            "fk": "212\n198\n220",
            "hs%": "100%\n100%\n100%",
            "kdr": "10\n6\n4",
            "kills": "345",
            "name": "Xenoo",
            "team": "Origin Sky"
          },
          {
            "acs": "1.39\n1.20\n1.49",
            "adr": "+6\n+1\n+5",
            "agent": "",
            "assists": "/\n\n14\n5\n9\n\n/",
            "deaths": "20\n6\n14",
            "fk": "193\n143\n221",
            "hs%": "95%\n86%\n100%",
            "kdr": "4\n2\n2",
            "kills": "316",
            "name": "IcaaaPftw",
            "team": "Origin Sky"
          },
          {
            "acs": "1.31\n1.75\n1.06",
            "adr": "+7\n+6\n+1",
            "agent": "",
            "assists": "/\n\n9\n1\n8\n\n/",
            "deaths": "16\n7\n9",
            "fk": "125\n94\n143",
            "hs%": "74%\n86%\n67%",
            "kdr": "6\n2\n4",
            "kills": "213",
            "name": "kayle",
            "team": "Origin Sky"
          },
          {
            "acs": "0.90\n1.39\n0.61",
            "adr": "-1\n+3\n-4",
            "agent": "",
            "assists": "/\n\n12\n3\n9\n\n/",
            "deaths": "11\n6\n5",
            "fk": "91\n112\n79",
            "hs%": "74%\n86%\n67%",
            "kdr": "8\n3\n5",
            "kills": "145",
            "name": "haze",
            "team": "Origin Sky"
          },
          {
            "acs": "0.73\n0.52\n0.85",
            "adr": "-2\n-2\n0",
            "agent": "",
            "assists": "/\n\n13\n5\n8\n\n/",
            "deaths": "11\n3\n8",
            "fk": "103\n91\n110",
            "hs%": "68%\n71%\n67%",
            "kdr": "3\n2\n1",
            "kills": "153",
            "name": "markL",
            "team": "Origin Sky"
          }
        ]
      ],
      "round_results": [],
      "total_score": null
    },
    {
      "flat_players": [
        {
          "kills": "451",
          "name": "Aanszo",
          "team": null
        },
        {
          "kills": "191",
          "name": "bryce",
          "team": null
        },
        {
          "kills": "147",
          "name": "JayH",
          "team": null
        },
        {
          "kills": "140",
          "name": "Flaring",
          "team": null
        },
        {
          "kills": "71",
          "name": "alfin",
          "team": null
        },
        {
          "kills": "361",
          "name": "Xenoo",
          "team": null
        },
        {
          "kills": "278",
          "name": "IcaaaPftw",
          "team": null
        },
        {
          "kills": "196",
          "name": "kayle",
          "team": null
        },
        {
          "kills": "208",
          "name": "haze",
          "team": null
        },
        {
          "kills": "126",
          "name": "markL",
          "team": null
        }
      ],
      "halftime_score": null,
      "map": "",
      "players": [
        [
          {
            "acs": "1.84\n0.36\n1.30",
            "adr": "+4\n+8\n-4",
            "agent": "",
            "assists": "/\n\n17\n12\n5\n\n/",
            "deaths": "21\n20\n1",
            "fk": "205\n263\n107",
            "hs%": "68%\n75%\n57%",
            "kdr": "5\n1\n4",
            "kills": "451",
            "name": "Aanszo",
            "team": null
          },
          {
            "acs": "1.06\n1.40\n1.18",
            "adr": "+2\n-1\n+3",
            "agent": "",
            "assists": "/\n\n15\n9\n6\n\n/",
            "deaths": "17\n8\n9",
            "fk": "159\n138\n194",
            "hs%": "84%\n92%\n71%",
            "kdr": "9\n8\n1",
            "kills": "191",
            "name": "bryce",
            "team": null
          },
          {
            "acs": "0.76\n0.21\n0.56",
            "adr": "-9\n-4\n-5",
            "agent": "",
            "assists": "/\n\n15\n9\n6\n\n/",
            "deaths": "6\n5\n1",
            "fk": "89\n119\n37",
            "hs%": "53%\n58%\n43%",
            "kdr": "6\n3\n3",
            "kills": "147",
            "name": "JayH",
            "team": null
          },
          {
            "acs": "0.35\n0.88\n0.54",
            "adr": "-7\n-8\n+1",
            "agent": "",
            "assists": "/\n\n17\n13\n4\n\n/",
            "deaths": "10\n5\n5",
            "fk": "112\n102\n128",
            "hs%": "63%\n58%\n71%",
            "kdr": "6\n3\n3",
            "kills": "140",
            "name": "Flaring",
            "team": null
          },
          {
            "acs": "0.26\n0.03\n0.16",
            "adr": "-13\n-7\n-6",
            "agent": "",
            "assists": "/\n\n17\n10\n7\n\n/",
            "deaths": "4\n3\n1",
            "fk": "44\n54\n27",
            "hs%": "37%\n50%\n14%",
            "kdr": "3\n3\n0",
            "kills": "71",
            "name": "alfin",
            "team": null
          }
        ],
        [
          {
            "acs": "1.89\n1.88\n1.88",
            "adr": "+13\n+5\n+8",
            "agent": "",
            "assists": "/\n\n10\n3\n7\n\n/",
            "deaths": "23\n8\n15",
            "fk": "212\n198\n220",
            "hs%": "100%\n100%\n100%",
            "kdr": "10\n6\n4",
            "kills": "361",
            "name": "Xenoo",
            "team": null
          },
          {
            "acs": "1.20\n1.49\n1.39",
            "adr": "+6\n+1\n+5",
            "agent": "",
            "assists": "/\n\n14\n5\n9\n\n/",
            "deaths": "20\n6\n14",
            "fk": "193\n143\n221",
            "hs%": "95%\n86%\n100%",
            "kdr": "4\n2\n2",
            "kills": "278",
            "name": "IcaaaPftw",
            "team": null
          },
          {
            "acs": "1.75\n1.06\n1.31",
            "adr": "+7\n+6\n+1",
            "agent": "",
            "assists": "/\n\n9\n1\n8\n\n/",
            "deaths": "16\n7\n9",
            "fk": "125\n94\n143",
            "hs%": "74%\n86%\n67%",
            "kdr": "6\n2\n4",
            "kills": "196",
            "name": "kayle",
            "team": null
          },
          {
            "acs": "1.39\n0.61\n0.90",
            "adr": "-1\n+3\n-4",
            "agent": "",
            "assists": "/\n\n12\n3\n9\n\n/",
            "deaths": "11\n6\n5",
            "fk": "91\n112\n79",
            "hs%": "74%\n86%\n67%",
            "kdr": "8\n3\n5",
            "kills": "208",
            "name": "haze",
            "team": null
          },
          {
            "acs": "0.52\n0.85\n0.73",
            "adr": "-2\n-2\n0",
            "agent": "",
            "assists": "/\n\n13\n5\n8\n\n/",
            "deaths": "11\n3\n8",
            "fk": "103\n91\n110",
            "hs%": "68%\n71%\n67%",
            "kdr": "3\n2\n1",
            "kills": "126",
            "name": "markL",
            "team": null
          }
        ]
      ],
      "round_results": [],
      "total_score": null
    }
  ],
  "maps": [],
  "match_id": 29879,
  "teams": [
    "Origin Sky",
    "uhrbtgjmny8"
  ],
  "tournament": "Qualifier: \n\t\t\t\t\t\tLast Chance Qualifier Semifinals"
}